relevance_libs/__init__.py
relevance_libs/elasticsearch.py
relevance_libs/schema.py
relevance_libs/sign.py
relevance_libs/analytics/__init__.py
relevance_libs/analytics/connector.py
relevance_libs/server/__init__.py
relevance_libs/server/middleware.py
relevance_libs/users/__init__.py
relevance_libs/users/connector.py
relevance_libs/users/models.py
relevance_libs-0.9.5.dist-info/LICENSE
relevance_libs-0.9.5.dist-info/METADATA
relevance_libs-0.9.5.dist-info/WHEEL
relevance_libs-0.9.5.dist-info/top_level.txt
relevance_libs-0.9.5.dist-info/RECORD
