Metadata-Version: 2.1
Name: relevance-libs
Version: 0.9.5
Summary: Relevance Python connectors.
Home-page: http://www.relevance.io
Author: Relevance.io
Author-email: info@relevance.io
Maintainer: Francis Lacroix
Maintainer-email: f@relevance.io
License: MIT
Platform: any
Classifier: Development Status :: 3 - Alpha
Classifier: Environment :: Console
Classifier: Intended Audience :: Information Technology
Classifier: Intended Audience :: Developers
Classifier: License :: OSI Approved :: MIT License
Classifier: Operating System :: OS Independent
Classifier: Programming Language :: Python :: 3
Classifier: Topic :: Software Development :: Libraries :: Python Modules
Provides: relevance_libs
Requires-Python: >=3.6
Requires-Dist: Flask (<2,>=1.1.1)
Requires-Dist: python-dateutil (<3,>=2.6.1)
Requires-Dist: requests (<3,>=2.9.1)
